{
  "localizedModules": [
    {
      "id": "module-alphabet",
      "title": "Alphabet"
    },
    {
      "id": "module-basic-vocabulary",
      "title": "Basic Vocabulary"
    }
  ],
  "localizedLessons": [
    {
      "id": "lesson-alphabet-vowels",
      "title": "The Five Vowels"
    },
    {
      "id": "lesson-alphabet-sounds-you-know",
      "title": "Sounds You Know"
    },
    {
      "id": "lesson-vocabulary-common-words",
      "title": "Common Words"
    }
  ],
  "localizedAlphabetItems": [
    {
      "id": "letter-ani",
      "pronunciationHint": "Like 'a' in 'father'"
    },
    {
      "id": "letter-eni",
      "pronunciationHint": "Like 'e' in 'bed'"
    },
    {
      "id": "letter-bani",
      "pronunciationHint": "Like 'b' in 'bed'"
    },
    {
      "id": "letter-gani",
      "pronunciationHint": "Like 'g' in 'go'"
    }
  ],
  "localizedVocabularyItems": [
    {
      "id": "word-gamarjoba",
      "translation": "hello"
    },
    {
      "id": "word-madloba",
      "translation": "thank you"
    }
  ]
}
